<annotation>
	<folder>rcnn-pic</folder>
	<filename>person-florida590.jpg</filename>
	<path>/home/wenyan/Pictures/rcnn-pic/person-florida590.jpg</path>
	<source>
		<database>Unknown</database>
	</source>
	<size>
		<width>3840</width>
		<height>2048</height>
		<depth>3</depth>
	</size>
	<segmented>0</segmented>
	<object>
		<name>person</name>
		<pose>Unspecified</pose>
		<truncated>0</truncated>
		<difficult>0</difficult>
		<bndbox>
			<xmin>2043</xmin>
			<ymin>950</ymin>
			<xmax>2188</xmax>
			<ymax>1450</ymax>
		</bndbox>
	</object>
	<object>
		<name>person</name>
		<pose>Unspecified</pose>
		<truncated>0</truncated>
		<difficult>0</difficult>
		<bndbox>
			<xmin>1712</xmin>
			<ymin>939</ymin>
			<xmax>1922</xmax>
			<ymax>1480</ymax>
		</bndbox>
	</object>
	<object>
		<name>car</name>
		<pose>Unspecified</pose>
		<truncated>0</truncated>
		<difficult>0</difficult>
		<bndbox>
			<xmin>1332</xmin>
			<ymin>974</ymin>
			<xmax>2207</xmax>
			<ymax>1398</ymax>
		</bndbox>
	</object>
	<object>
		<name>sign</name>
		<pose>Unspecified</pose>
		<truncated>0</truncated>
		<difficult>0</difficult>
		<bndbox>
			<xmin>1159</xmin>
			<ymin>983</ymin>
			<xmax>1187</xmax>
			<ymax>1002</ymax>
		</bndbox>
	</object>
	<object>
		<name>sign</name>
		<pose>Unspecified</pose>
		<truncated>0</truncated>
		<difficult>0</difficult>
		<bndbox>
			<xmin>1093</xmin>
			<ymin>920</ymin>
			<xmax>1136</xmax>
			<ymax>967</ymax>
		</bndbox>
	</object>
	<object>
		<name>car</name>
		<pose>Unspecified</pose>
		<truncated>0</truncated>
		<difficult>0</difficult>
		<bndbox>
			<xmin>694</xmin>
			<ymin>1022</ymin>
			<xmax>742</xmax>
			<ymax>1048</ymax>
		</bndbox>
	</object>
	<object>
		<name>boat</name>
		<pose>Unspecified</pose>
		<truncated>0</truncated>
		<difficult>0</difficult>
		<bndbox>
			<xmin>2184</xmin>
			<ymin>1057</ymin>
			<xmax>2498</xmax>
			<ymax>1177</ymax>
		</bndbox>
	</object>
	<object>
		<name>boat</name>
		<pose>Unspecified</pose>
		<truncated>0</truncated>
		<difficult>0</difficult>
		<bndbox>
			<xmin>2637</xmin>
			<ymin>990</ymin>
			<xmax>2756</xmax>
			<ymax>1063</ymax>
		</bndbox>
	</object>
	<object>
		<name>boat</name>
		<pose>Unspecified</pose>
		<truncated>0</truncated>
		<difficult>0</difficult>
		<bndbox>
			<xmin>2760</xmin>
			<ymin>1015</ymin>
			<xmax>2844</xmax>
			<ymax>1044</ymax>
		</bndbox>
	</object>
	<object>
		<name>boat</name>
		<pose>Unspecified</pose>
		<truncated>0</truncated>
		<difficult>0</difficult>
		<bndbox>
			<xmin>2803</xmin>
			<ymin>1012</ymin>
			<xmax>2888</xmax>
			<ymax>1040</ymax>
		</bndbox>
	</object>
	<object>
		<name>sign</name>
		<pose>Unspecified</pose>
		<truncated>0</truncated>
		<difficult>0</difficult>
		<bndbox>
			<xmin>1087</xmin>
			<ymin>985</ymin>
			<xmax>1100</xmax>
			<ymax>999</ymax>
		</bndbox>
	</object>
	<object>
		<name>sign</name>
		<pose>Unspecified</pose>
		<truncated>0</truncated>
		<difficult>0</difficult>
		<bndbox>
			<xmin>1137</xmin>
			<ymin>984</ymin>
			<xmax>1151</xmax>
			<ymax>1000</ymax>
		</bndbox>
	</object>
	<object>
		<name>sign</name>
		<pose>Unspecified</pose>
		<truncated>0</truncated>
		<difficult>0</difficult>
		<bndbox>
			<xmin>1191</xmin>
			<ymin>984</ymin>
			<xmax>1204</xmax>
			<ymax>998</ymax>
		</bndbox>
	</object>
	<object>
		<name>truck</name>
		<pose>Unspecified</pose>
		<truncated>0</truncated>
		<difficult>0</difficult>
		<bndbox>
			<xmin>2224</xmin>
			<ymin>985</ymin>
			<xmax>2257</xmax>
			<ymax>1010</ymax>
		</bndbox>
	</object>
</annotation>
