<annotation>
  <folder></folder>
  <filename>person-florida5150</filename>
  <path> </path>
  <source>
    <database>  </database>
  </source>
  <size>
    <width>3840</width>
    <height>2048</height>
    <depth>3</depth>
  </size>
  <segmented>0</segmented>
  <object>
    <name>fish</name>
    <pose>Unspecified</pose>
    <truncated>0</truncated>
    <difficult>0</difficult>
    <bndbox>
      <xmin>2423</xmin>
      <ymin>1473</ymin>
      <xmax>2867</xmax>
      <ymax>1709</ymax>
    </bndbox>
  </object>
  <object>
    <name>person</name>
    <pose>Unspecified</pose>
    <truncated>0</truncated>
    <difficult>0</difficult>
    <bndbox>
      <xmin>1095</xmin>
      <ymin>727</ymin>
      <xmax>1197</xmax>
      <ymax>892</ymax>
    </bndbox>
  </object>
  <object>
    <name>person</name>
    <pose>Unspecified</pose>
    <truncated>0</truncated>
    <difficult>0</difficult>
    <bndbox>
      <xmin>915</xmin>
      <ymin>724</ymin>
      <xmax>1122</xmax>
      <ymax>1110</ymax>
    </bndbox>
  </object>
  <object>
    <name>person</name>
    <pose>Unspecified</pose>
    <truncated>0</truncated>
    <difficult>0</difficult>
    <bndbox>
      <xmin>782</xmin>
      <ymin>693</ymin>
      <xmax>895</xmax>
      <ymax>881</ymax>
    </bndbox>
  </object>
  <object>
    <name>boat</name>
    <pose>Unspecified</pose>
    <truncated>0</truncated>
    <difficult>0</difficult>
    <bndbox>
      <xmin>5</xmin>
      <ymin>833</ymin>
      <xmax>1372</xmax>
      <ymax>1466</ymax>
    </bndbox>
  </object>
</annotation>