<annotation>
	<folder>2blabel</folder>
	<filename>person-pocker3450.jpg</filename>
	<path>/home/wenyan/Pictures/2blabel/person-pocker3450.jpg</path>
	<source>
		<database>Unknown</database>
	</source>
	<size>
		<width>3840</width>
		<height>1920</height>
		<depth>3</depth>
	</size>
	<segmented>0</segmented>
	<object>
		<name>person</name>
		<pose>Unspecified</pose>
		<truncated>0</truncated>
		<difficult>0</difficult>
		<bndbox>
			<xmin>1203</xmin>
			<ymin>899</ymin>
			<xmax>1331</xmax>
			<ymax>1372</ymax>
		</bndbox>
	</object>
	<object>
		<name>person</name>
		<pose>Unspecified</pose>
		<truncated>0</truncated>
		<difficult>0</difficult>
		<bndbox>
			<xmin>1216</xmin>
			<ymin>760</ymin>
			<xmax>1538</xmax>
			<ymax>1547</ymax>
		</bndbox>
	</object>
	<object>
		<name>person</name>
		<pose>Unspecified</pose>
		<truncated>0</truncated>
		<difficult>0</difficult>
		<bndbox>
			<xmin>1618</xmin>
			<ymin>865</ymin>
			<xmax>2133</xmax>
			<ymax>1529</ymax>
		</bndbox>
	</object>
</annotation>
