<annotation>
  <folder></folder>
  <filename>person-yard965</filename>
  <path> </path>
  <source>
    <database>  </database>
  </source>
  <size>
    <width>3840</width>
    <height>2048</height>
    <depth>3</depth>
  </size>
  <segmented>0</segmented>
  <object>
    <name>person</name>
    <pose>Unspecified</pose>
    <truncated>0</truncated>
    <difficult>0</difficult>
    <bndbox>
      <xmin>1903</xmin>
      <ymin>975</ymin>
      <xmax>1976</xmax>
      <ymax>1229</ymax>
    </bndbox>
  </object>
  <object>
    <name>person</name>
    <pose>Unspecified</pose>
    <truncated>0</truncated>
    <difficult>0</difficult>
    <bndbox>
      <xmin>3483</xmin>
      <ymin>981</ymin>
      <xmax>3539</xmax>
      <ymax>1117</ymax>
    </bndbox>
  </object>
  <object>
    <name>person</name>
    <pose>Unspecified</pose>
    <truncated>0</truncated>
    <difficult>0</difficult>
    <bndbox>
      <xmin>143</xmin>
      <ymin>964</ymin>
      <xmax>238</xmax>
      <ymax>1281</ymax>
    </bndbox>
  </object>
  <object>
    <name>person</name>
    <pose>Unspecified</pose>
    <truncated>0</truncated>
    <difficult>0</difficult>
    <bndbox>
      <xmin>397</xmin>
      <ymin>979</ymin>
      <xmax>464</xmax>
      <ymax>1158</ymax>
    </bndbox>
  </object>
  <object>
    <name>person</name>
    <pose>Unspecified</pose>
    <truncated>0</truncated>
    <difficult>0</difficult>
    <bndbox>
      <xmin>515</xmin>
      <ymin>987</ymin>
      <xmax>621</xmax>
      <ymax>1303</ymax>
    </bndbox>
  </object>
</annotation>